Workbook

Sheet Summary
A1: Call Campaign Summary
A3: Total Leads | B3: =COUNTA('Call Tracker'!A2:A285) -> 284
A4: Not Started | B4: =COUNTIF('Call Tracker'!G2:G285,"Not Started") -> 284
A5: Attempted (No Answer/Voicemail/Gatekeeper) | B5: =COUNTIF('Call Tracker'!G2:G285,"Attempted - No Answer")+COUNTIF('Call Tracker'!G2:G285,"Attempted - Voicemail")+COUNTIF('Call Tracker'!G2:G285,"Gatekeeper") -> 0
A6: Spoke - Interested / Follow-up Scheduled | B6: =COUNTIF('Call Tracker'!G2:G285,"Spoke - Interested")+COUNTIF('Call Tracker'!G2:G285,"Follow-up Scheduled") -> 0
A7: Meetings Booked | B7: =COUNTIF('Call Tracker'!G2:G285,"Meeting Booked") -> 0
A8: Closed Won | B8: =COUNTIF('Call Tracker'!G2:G285,"Closed Won") -> 0
A9: Closed Lost / Not Interested | B9: =COUNTIF('Call Tracker'!G2:G285,"Closed Lost")+COUNTIF('Call Tracker'!G2:G285,"Spoke - Not Interested") -> 0
A10: Bad Number / DNC | B10: =COUNTIF('Call Tracker'!G2:G285,"Bad Number/DNC") -> 0

Sheet Hot Leads (Top 100)
A1: Priority Rank | B1: Industry | C1: Business Name | D1: Owner / Key Contact | E1: Phone | F1: Email | G1: Website | H1: LinkedIn | I1: City, State | J1: Google Rating (count) | K1: Why It's Hot | L1: Notes / Verify on Call
A2: 1 | B2: Logistics | C2: First Mile Transportation LLC | D2: Bernard Baggett (CEO) | E2: +1 513-964-7021 | F2: Not public - website contact form | G2: firstmiletransportationllc.com | H2: linkedin.com/company/first-mile-transportation-llc | I2: Cincinnati, OH | J2: 1 | K2: Brand-new/very small carrier, minimal footprint | L2: Strong automation-gap candidate
A3: 2 | B3: Logistics | C3: Monster Logistics LLC | D3: Justin Allen Monter (owner, per FMCSA filing) | E3: +1 330-274-4280 | F3: Not public - website contact form | G3: monsterlogistics.com | H3: Verify - linked from monsterlogistics.com footer | I3: Akron, OH | J3: 1 | K3: Very small/new brokerage, minimal footprint | L3: Strong automation-gap candidate
A4: 3 | B4: Logistics | C4: Taylor Transports | D4: Not identified - confirm on call | E4: +1 937-949-5309 | F4: Not public - website contact form | G4: taylorfreight.com | H4: Not found - verify on call | I4: Dayton, OH | J4: 1 | K4: Very small/new carrier, minimal footprint | L4: Strong automation-gap candidate
A5: 4 | B5: Logistics | C5: Premier LTL Transportation Inc | D5: Maria Lopez (staff - confirm owner) | E5: +1 714-660-9090 | F5: Not public - website contact form | G5: premiertransportationinc.com | H5: Not found - verify on call | I5: Anaheim, CA | J5: 1 | K5: Very small/new freight carrier | L5: Strong automation-gap candidate
A6: 5 | B6: Logistics | C6: Allegiance Trucking, LLC | D6: Not identified - confirm on call | E6: +1 806-584-4650 | F6: Not public - website contact form | G6: allegiancetruckingco.com | H6: Not found - verify on call | I6: Amarillo, TX | J6: 1 | K6: Very small/new carrier, minimal footprint | L6: Strong automation-gap candidate
A7: 6 | B7: Logistics | C7: Abdi Transport Inc | D7: Abdi Aden (President) / Abdirahman Farah (VP) | E7: +1 614-591-4080 | F7: Not public - website contact form | G7: abditransportinc.com | H7: Not found - verify on call | I7: Columbus, OH | J7: 2 | K7: Very small, owner hands-on per reviews | L7: Strong automation-gap candidate
A8: 7 | B8: Logistics | C8: Esco's Trucking LLC | D8: Silvia and Guillermo (owners) | E8: +1 210-815-9412 | F8: Not public - website contact form | G8: Website not confirmed - verify | H8: Search "Esco's Trucking San Antonio" on LinkedIn | I8: San Antonio, TX | J8: 2 | K8: Very small carrier, minimal online footprint | L8: Strong automation-gap candidate
A9: 8 | B9: Logistics | C9: Schwerman Trucking Co | D9: Not identified - confirm on call | E9: +1 254-776-1012 | F9: Not public - website contact form | G9: Website not confirmed - verify | H9: Search 'Schwerman Trucking Waco' on LinkedIn | I9: Waco, TX | J9: 2 | K9: Very small/new location, minimal footprint | L9: Strong automation-gap candidate
A10: 9 | B10: Logistics | C10: Marathon Transportation and Logistics, inc | D10: Not identified - confirm on call | E10: +1 706-442-0094 | F10: Not public - website contact form | G10: Website not confirmed - verify | H10: Search 'Marathon Transportation Logistics Columbus GA' on LinkedIn | I10: Columbus, GA | J10: 2 | K10: Very small/new carrier, minimal footprint | L10: Strong automation-gap candidate
A11: 10 | B11: Logistics | C11: Austin Texas Transport LLC | D11: Martin (staff/owner - confirm) | E11: +1 512-679-4671 | F11: Not public - website contact form | G11: Website not confirmed - verify | H11: Search 'Austin Texas Transport LLC' on LinkedIn | I11: Austin, TX | J11: 3 | K11: Very small local/regional carrier | L11: Strong automation-gap candidate
A12: 11 | B12: Logistics | C12: Revive Transport | D12: Not identified - confirm on call | E12: +1 567-314-9696 | F12: Not public - website contact form | G12: Website not confirmed - verify | H12: Search 'Revive Transport Toledo' on LinkedIn | I12: Toledo, OH | J12: 3 | K12: Very small local carrier | L12: Strong automation-gap candidate
A13: 12 | B13: Real Estate | C13: Independent Realty | D13: Not identified - confirm on call | E13: +1 510-278-5800 | F13: Not public - website contact form | G13: Website not confirmed - verify | H13: Search 'Independent Realty San Leandro' on LinkedIn | I13: San Leandro, CA | J13: 3 | K13: Very small shop, low review count | L13: Strong automation-gap candidate
... A101: 100 | B101: Logistics | C101: RamRod Trucking, Inc | D101: Richard / Eysla (dispatch - confirm owner) | E101: +1 713-699-5757 | F101: Not public - website contact form | G101: ramrodtrucking.com (verify) | H101: Search 'RamRod Trucking Houston' on LinkedIn | I101: Houston, TX | J101: 33 | K101: Multi-branch hotshot/flatbed carrier, phone-based dispatch | L101: Strong automation-gap candidate

Sheet Leads
A1: # | B1: Industry | C1: Business Name | D1: Owner / Key Contact | E1: Phone | F1: Email | G1: Website | H1: LinkedIn | I1: City, State | J1: Google Rating (count) | K1: Digital Maturity Signal | L1: Notes / Verify on Call
A2: 1 | B2: Real Estate | C2: Ms. Houston Real Estate | D2: Katy To (owner/agent) | E2: +1 346-327-5787 | F2: Not public - use website contact form | G2: mshoustonrealestate.com | H2: linkedin.com/company/ms-houston-real-estate | I2: Houston, TX | J2: 90 | K2: Small independent, review-driven, no visible booking automation | L2: Verify owner title on call
A3: 2 | B3: Real Estate | C3: Jay Thomas Real Estate Team | D3: Jay Thomas (team leader) | E3: +1 832-889-5607 | F3: Not public - website contact form | G3: buywithjaythomas.com | H3: linkedin.com/in/thejaythomasteam | I3: Houston, TX | J3: 132 | K3: Solo/small team brand, manual lead follow-up likely | L3: Verify owner title on call
A4: 3 | B4: Real Estate | C4: City Group Properties - Real Estate Brokerage | D4: Alex DiSaggio (Broker) | E4: +1 713-843-7284 | F4: Not public - website contact form | G4: citygroupproperties.com | H4: Not confidently found - verify on call | I4: Houston, TX | J4: 129 | K4: Boutique brokerage, several individual agents | L4: Ask for broker/owner name
A5: 4 | B5: Real Estate | C5: Evan Downey Real Estate Group, eXp Realty | D5: Evan Downey (Broker Associate) | E5: +1 214-997-4929 | F5: Not public - website contact form | G5: evandowneyrealestate.com | H5: Not confidently matched (namesake conflict) - verify on call | I5: Dallas, TX | J5: 200 | K5: eXp affiliated but small local team | L5: Confirm CRM/automation currently used
A6: 5 | B6: Real Estate | C6: Van Poole Properties Group, Keller Williams | D6: Seychelle Van Poole Engelhard (CEO) | E6: +1 214-267-9222 | F6: Not public - website contact form | G6: vanpooleproperties.com | H6: linkedin.com/company/van-poole-properties-group | I6: Dallas, TX | J6: 184 | K6: Multi-agent KW team, mixed digital maturity | L6: Ask who owns lead intake process
A7: 6 | B7: Real Estate | C7: Dallas & Beyond Real Estate Group | D7: Mani & Eve (principals - confirm) | E7: +1 469-451-6330 | F7: Not public - website contact form | G7: dallasandbeyond.com (verify) | H7: Search 'Dallas and Beyond Real Estate' on LinkedIn | I7: Lewisville, TX | J7: 151 | K7: Small boutique team, personal-touch service model | L7: Verify legal owner name
A8: 7 | B8: Real Estate | C8: Method Real Estate Advisors | D8: Not identified - confirm on call | E8: +1 404-585-7355 | F8: Not public - website contact form | G8: methodrealestate.com (verify) | H8: Search 'Method Real Estate Advisors' on LinkedIn | I8: Roswell, GA | J8: 215 | K8: Independent brokerage, multiple solo agents | L8: Ask for managing broker name
A9: 8 | B9: Real Estate | C9: EmpowerHome Team Atlanta | D9: Not identified - confirm on call | E9: +1 404-974-4922 | F9: Not public - website contact form | G9: empowerhometeam.com (verify) | H9: Search 'EmpowerHome Team Atlanta' on LinkedIn | I9: Atlanta, GA | J9: 539 | K9: National brand local team - moderate digital maturity | L9: May already use some automation - qualify first
A10: 9 | B10: Real Estate | C10: Anna K Intown Real Estate Team | D10: Anna K (team founder - confirm) | E10: +1 678-400-9151 | F10: Not public - website contact form | G10: annakintown.com (verify) | H10: Search 'Anna K Intown Real Estate' on LinkedIn | I10: Atlanta, GA | J10: 633 | K10: Larger team, specialized roles per stage of deal | L10: Qualify automation gaps before pitching
A11: 10 | B11: Real Estate | C11: Affordable Real Estate Company | D11: Vanessa (agent - confirm owner) | E11: +1 614-884-3300 | F11: Not public - website contact form | G11: Website not confirmed - verify | H11: Search 'Affordable Real Estate Company Columbus' on LinkedIn | I11: Columbus, OH | J11: 37 | K11: Small shop, limited hours (closed weekends), likely manual | L11: Strong automation-gap candidate
A12: 11 | B12: Real Estate | C12: Kendle Real Estate Team | D12: Ron Kendle (team lead) | E12: +1 614-325-6295 | F12: Not public - website contact form | G12: kendleteam.com (verify) | H12: Search 'Ron Kendle Real Estate' on LinkedIn | I12: Columbus, OH | J12: 37 | K12: RE/MAX affiliated small local team | L12: Verify current tools in use
A13: 12 | B13: Real Estate | C13: Lee Ritchie Realtor | Ritchie Realty Group | D13: Lee Ritchie (owner/agent) | E13: +1 614-595-0732 | F13: Not public - website contact form | G13: ritchierealtygroup.com (verify) | H13: Search 'Lee Ritchie Realtor Columbus' on LinkedIn | I13: Columbus, OH | J13: 129 | K13: Independent RE/MAX Partners team | L13: Verify owner title on call
... A285: 284 | B285: Logistics | C285: Roth Trucking Inc | D285: Not identified - confirm on call | E285: +1 800-522-7684 | F285: Not public - website contact form | G285: Website not confirmed - verify | H285: Search 'Roth Trucking Grand Rapids' on LinkedIn | I285: Grand Rapids, MI | J285: 23 | K285: Small regional carrier | L285: Strong automation-gap candidate

Sheet Call Tracker
A1: # | B1: Business Name | C1: Industry | D1: City, State | E1: Phone | F1: Owner / Key Contact | G1: Call Status | H1: Attempts | I1: Last Contact Date | J1: Next Follow-up Date | K1: Assigned Rep | L1: Outcome Notes
A2: =Leads!A2 -> 1 | B2: =Leads!C2 -> Ms. Houston Real Estate | C2: =Leads!B2 -> Real Estate | D2: =Leads!I2 -> Houston, TX | E2: =Leads!E2 -> +1 346-327-5787 | F2: =Leads!D2 -> Katy To (owner/agent) | G2: Not Started | H2: 0
A3: =Leads!A3 -> 2 | B3: =Leads!C3 -> Jay Thomas Real Estate Team | C3: =Leads!B3 -> Real Estate | D3: =Leads!I3 -> Houston, TX | E3: =Leads!E3 -> +1 832-889-5607 | F3: =Leads!D3 -> Jay Thomas (team leader) | G3: Not Started | H3: 0
A4: =Leads!A4 -> 3 | B4: =Leads!C4 -> City Group Properties - Real Estate Brokerage | C4: =Leads!B4 -> Real Estate | D4: =Leads!I4 -> Houston, TX | E4: =Leads!E4 -> +1 713-843-7284 | F4: =Leads!D4 -> Alex DiSaggio (Broker) | G4: Not Started | H4: 0
A5: =Leads!A5 -> 4 | B5: =Leads!C5 -> Evan Downey Real Estate Group, eXp Realty | C5: =Leads!B5 -> Real Estate | D5: =Leads!I5 -> Dallas, TX | E5: =Leads!E5 -> +1 214-997-4929 | F5: =Leads!D5 -> Evan Downey (Broker Associate) | G5: Not Started | H5: 0
A6: =Leads!A6 -> 5 | B6: =Leads!C6 -> Van Poole Properties Group, Keller Williams | C6: =Leads!B6 -> Real Estate | D6: =Leads!I6 -> Dallas, TX | E6: =Leads!E6 -> +1 214-267-9222 | F6: =Leads!D6 -> Seychelle Van Poole Engelhard (CEO) | G6: Not Started | H6: 0
A7: =Leads!A7 -> 6 | B7: =Leads!C7 -> Dallas & Beyond Real Estate Group | C7: =Leads!B7 -> Real Estate | D7: =Leads!I7 -> Lewisville, TX | E7: =Leads!E7 -> +1 469-451-6330 | F7: =Leads!D7 -> Mani & Eve (principals - confirm) | G7: Not Started | H7: 0
A8: =Leads!A8 -> 7 | B8: =Leads!C8 -> Method Real Estate Advisors | C8: =Leads!B8 -> Real Estate | D8: =Leads!I8 -> Roswell, GA | E8: =Leads!E8 -> +1 404-585-7355 | F8: =Leads!D8 -> Not identified - confirm on call | G8: Not Started | H8: 0
A9: =Leads!A9 -> 8 | B9: =Leads!C9 -> EmpowerHome Team Atlanta | C9: =Leads!B9 -> Real Estate | D9: =Leads!I9 -> Atlanta, GA | E9: =Leads!E9 -> +1 404-974-4922 | F9: =Leads!D9 -> Not identified - confirm on call | G9: Not Started | H9: 0
A10: =Leads!A10 -> 9 | B10: =Leads!C10 -> Anna K Intown Real Estate Team | C10: =Leads!B10 -> Real Estate | D10: =Leads!I10 -> Atlanta, GA | E10: =Leads!E10 -> +1 678-400-9151 | F10: =Leads!D10 -> Anna K (team founder - confirm) | G10: Not Started | H10: 0
A11: =Leads!A11 -> 10 | B11: =Leads!C11 -> Affordable Real Estate Company | C11: =Leads!B11 -> Real Estate | D11: =Leads!I11 -> Columbus, OH | E11: =Leads!E11 -> +1 614-884-3300 | F11: =Leads!D11 -> Vanessa (agent - confirm owner) | G11: Not Started | H11: 0
A12: =Leads!A12 -> 11 | B12: =Leads!C12 -> Kendle Real Estate Team | C12: =Leads!B12 -> Real Estate | D12: =Leads!I12 -> Columbus, OH | E12: =Leads!E12 -> +1 614-325-6295 | F12: =Leads!D12 -> Ron Kendle (team lead) | G12: Not Started | H12: 0
A13: =Leads!A13 -> 12 | B13: =Leads!C13 -> Lee Ritchie Realtor | Ritchie Realty Group | C13: =Leads!B13 -> Real Estate | D13: =Leads!I13 -> Columbus, OH | E13: =Leads!E13 -> +1 614-595-0732 | F13: =Leads!D13 -> Lee Ritchie (owner/agent) | G13: Not Started | H13: 0
... A285: =Leads!A285 -> 284 | B285: =Leads!C285 -> Roth Trucking Inc | C285: =Leads!B285 -> Logistics | D285: =Leads!I285 -> Grand Rapids, MI | E285: =Leads!E285 -> +1 800-522-7684 | F285: =Leads!D285 -> Not identified - confirm on call | G285: Not Started | H285: 0

Sheet Mid-Market Logistics
A1: # | B1: Company Name | C1: State | D1: Employee Size Bracket | E1: Founded | F1: Description | G1: Phone | H1: Email | I1: Website | J1: LinkedIn | K1: Notes
A2: 1 | B2: Lonestar Transportation LLC | C2: TX | D2: 201-500 | F2: Truckload carrier | G2: Not public - verify on call | H2: Not public - website contact form | I2: Website not confirmed - verify | J2: Search 'Lonestar Transportation LLC Texas' on LinkedIn | K2: Verify contact details - sourced via Indeed company size data, not GBP
A3: 2 | B3: Empire Truck Lines | C3: TX | D3: 201-500 | E3: 1975 | F3: Trucking and logistics carrier | G3: Not public - verify on call | H3: Not public - website contact form | I3: Website not confirmed - verify | J3: Search 'Empire Truck Lines Texas' on LinkedIn | K3: Verify contact details
A4: 3 | B4: Palletized Trucking | C4: TX | D4: 201-500 | E4: 1969 | F4: Trucking and logistics carrier | G4: Not public - verify on call | H4: Not public - website contact form | I4: Website not confirmed - verify | J4: Search 'Palletized Trucking Texas' on LinkedIn | K4: Verify contact details
A5: 4 | B5: Butler Transport | C5: TX | D5: 51-200 | F5: Regional trucking carrier | G5: Not public - verify on call | H5: Not public - website contact form | I5: Website not confirmed - verify | J5: Search 'Butler Transport Texas' on LinkedIn | K5: Verify contact details
A6: 5 | B6: JA Harris Trucking Inc | C6: TX | D6: 11-50 | F6: Regional trucking carrier | G6: Not public - verify on call | H6: Not public - website contact form | I6: Website not confirmed - verify | J6: Search 'JA Harris Trucking Texas' on LinkedIn | K6: Verify contact details
A7: 6 | B7: Summit Trucking | C7: TX | D7: 11-50 | F7: Regional trucking carrier | G7: Not public - verify on call | H7: Not public - website contact form | I7: Website not confirmed - verify | J7: Search 'Summit Trucking Texas' on LinkedIn | K7: Verify contact details
A8: 7 | B8: Redbird Trucking | C8: TX | D8: 11-50 | F8: Regional trucking carrier | G8: Not public - verify on call | H8: Not public - website contact form | I8: Website not confirmed - verify | J8: Search 'Redbird Trucking Texas' on LinkedIn | K8: Verify contact details
A9: 8 | B9: Hot Shot Trucking | C9: TX | D9: 11-50 | F9: Hotshot/expedited carrier | G9: Not public - verify on call | H9: Not public - website contact form | I9: Website not confirmed - verify | J9: Search 'Hot Shot Trucking Texas' on LinkedIn | K9: Verify contact details
A10: 9 | B10: Flex Trucking Company LLC | C10: TX | D10: 2-10 | F10: Small regional carrier | G10: Not public - verify on call | H10: Not public - website contact form | I10: Website not confirmed - verify | J10: Search 'Flex Trucking Company Texas' on LinkedIn | K10: Verify contact details
A11: 10 | B11: Kennesaw Transportation | C11: GA | D11: 201-500 | F11: Trucking and logistics carrier (~350 employees, $50M+ revenue per listing) | G11: Not public - verify on call | H11: Not public - website contact form | I11: Website not confirmed - verify | J11: Search 'Kennesaw Transportation Georgia' on LinkedIn | K11: Verify contact details
A12: 11 | B12: Broadleaf Trucking | C12: GA | D12: 51-200 | F12: Regional trucking carrier | G12: Not public - verify on call | H12: Not public - website contact form | I12: Website not confirmed - verify | J12: Search 'Broadleaf Trucking Georgia' on LinkedIn | K12: Verify contact details
A13: 12 | B13: IST Logistics | C13: GA | D13: 51-200 | F13: Logistics and warehousing (HQ Indiana, GA location) | G13: Not public - verify on call | H13: Not public - website contact form | I13: Website not confirmed - verify | J13: Search 'IST Logistics Georgia' on LinkedIn | K13: Verify contact details
A14: 13 | B14: Preferred Transport & Distribution | C14: GA | D14: 11-50 | F14: Regional trucking carrier | G14: Not public - verify on call | H14: Not public - website contact form | I14: Website not confirmed - verify | J14: Search 'Preferred Transport and Distribution Georgia' on LinkedIn | K14: Verify contact details
A15: 14 | B15: Volume Transportation | C15: GA | D15: <10 | F15: Small regional carrier | G15: Not public - verify on call | H15: Not public - website contact form | I15: Website not confirmed - verify | J15: Search 'Volume Transportation Georgia' on LinkedIn | K15: Verify contact details
A16: 15 | B16: Meyers Bros Trucking | C16: OH | D16: 51-200 | E16: 2003 | F16: Truckload, local delivery, expedited freight, storage/rental trailer service | G16: Not public - verify on call | H16: Not public - website contact form | I16: Website not confirmed - verify | J16: Search 'Meyers Bros Trucking Ohio' on LinkedIn | K16: Verify contact details
A17: 16 | B17: TP Freight Lines | C17: OR | D17: 50-200 | E17: 1922 | F17: Pacific Northwest general freight carrier | G17: Not public - verify on call | H17: Not public - website contact form | I17: Website not confirmed - verify | J17: Search 'TP Freight Lines Oregon' on LinkedIn | K17: Verify contact details
A18: 17 | B18: Carroll Fulmer Logistics Corporation | C18: FL | D18: 201-500 | E18: 1953 | F18: Trucking, freight and logistics, online shipment tracking | G18: Not public - verify on call | H18: Not public - website contact form | I18: Website not confirmed - verify | J18: Search 'Carroll Fulmer Logistics Florida' on LinkedIn | K18: Verify contact details
A19: 18 | B19: Indian River Transport | C19: FL | D19: 201-500 | E19: 1974 | F19: Bulk liquid transport, national and international (Canada/Mexico) | G19: Not public - verify on call | H19: Not public - website contact form | I19: Website not confirmed - verify | J19: Search 'Indian River Transport Florida' on LinkedIn | K19: Verify contact details
A20: 19 | B20: Inland Transport Inc. | C20: FL | D20: 201-500 | E20: 1997 | F20: Transportation, logistics planning, warehouse distribution (US/Canada/Mexico) | G20: Not public - verify on call | H20: Not public - website contact form | I20: Website not confirmed - verify | J20: Search 'Inland Transport Inc Orlando' on LinkedIn | K20: Verify contact details
A21: 20 | B21: Florida Beauty Flora | C21: FL | D21: 11-50 | E21: 1983 | F21: 3PL, transportation, warehouse distribution - refrigerated fleet | G21: Not public - verify on call | H21: Not public - website contact form | I21: Website not confirmed - verify | J21: Search 'Florida Beauty Flora' on LinkedIn | K21: Verify contact details
A22: 21 | B22: Coast to Coast Trucking Inc. | C22: FL | D22: 11-50 | E22: 1996 | F22: Domestic and international transportation/logistics | G22: Not public - verify on call | H22: Not public - website contact form | I22: Website not confirmed - verify | J22: Search 'Coast to Coast Trucking Inc Florida' on LinkedIn | K22: Verify contact details
A23: 22 | B23: Lake Trucking Company | C23: FL | D23: 11-50 | E23: 1961 | F23: Refrigerated trucking - seafood, meats, perishables | G23: Not public - verify on call | H23: Not public - website contact form | I23: Website not confirmed - verify | J23: Search 'Lake Trucking Company Florida' on LinkedIn | K23: Verify contact details
A24: 23 | B24: Service Trucking | C24: FL | D24: 11-50 | E24: 1976 | F24: Long-haul trucking - refrigerated and dry goods | G24: Not public - verify on call | H24: Not public - website contact form | I24: Website not confirmed - verify | J24: Search 'Service Trucking Florida' on LinkedIn | K24: Verify contact details
A25: 24 | B25: E.W. Wylie Corporation | C25: AZ | D25: 201-500 | E25: 1938 | F25: Step deck/flatbed transportation, Glass Hauling Division | G25: Not public - verify on call | H25: Not public - website contact form | I25: Website not confirmed - verify | J25: Search 'E.W. Wylie Corporation Arizona' on LinkedIn | K25: Verify contact details
A26: 25 | B26: Northland Trucking, Inc. | C26: AZ | D26: 51-200 | E26: 1978 | F26: Truckload, freight consolidation, flatbed, drop trucks | G26: Not public - verify on call | H26: Not public - website contact form | I26: Website not confirmed - verify | J26: Search 'Northland Trucking Arizona' on LinkedIn | K26: Verify contact details
